LICENCE.md
MANIFEST.in
README.rst
setup.py
django_highrise/__init__.py
django_highrise/models.py
django_highrise/tests.py
django_highrise.egg-info/PKG-INFO
django_highrise.egg-info/SOURCES.txt
django_highrise.egg-info/dependency_links.txt
django_highrise.egg-info/requires.txt
django_highrise.egg-info/top_level.txt