Metadata-Version: 1.1
Name: django-highrise
Version: 0.6
Summary: Highrise CRM integration for Django projects.
Home-page: https://github.com/hugorodgerbrown/django-highrise
Author: Hugo Rodger-Brown
Author-email: hugo@rodger-brown.com
License: Copyright (c) 2013, Hugo Rodger-Brown
